default_scraper/__init__.py
default_scraper/drivers/chromedriver
default_scraper/googleplay/__init__.py
default_scraper/googleplay/review/__init__.py
default_scraper/googleplay/review/parser.py
default_scraper/instagram/__init__.py
default_scraper/instagram/dto.py
default_scraper/instagram/parser.py
default_scraper/instagram/signin.py
default_scraper/instagram/webdriver.py
default_scraper-1.1.1.dist-info/METADATA
default_scraper-1.1.1.dist-info/WHEEL
default_scraper-1.1.1.dist-info/top_level.txt
default_scraper-1.1.1.dist-info/zip-safe
default_scraper-1.1.1.dist-info/RECORD
